rxiter/__init__.py
rxiter/main.py
rxiter/tools.py
rxiter-0.0.7.dist-info/METADATA
rxiter-0.0.7.dist-info/WHEEL
rxiter-0.0.7.dist-info/top_level.txt
rxiter-0.0.7.dist-info/RECORD
