Metadata-Version: 2.1
Name: rxiter
Version: 0.0.7
Summary: Observable operations for async generators
License: MIT
Classifier: Development Status :: 6 - Mature
Classifier: Environment :: Console
Classifier: Intended Audience :: Developers
Classifier: License :: OSI Approved :: MIT License
Classifier: Programming Language :: Python
